{
  "cardId": "indian-national-army",
  "questions": [
    {
      "id": "indian-national-army-q01",
      "difficulty": "easy",
      "q": "By what Hindi name is the Indian National Army also widely known?",
      "options": [
        "Azad Hind Fauj",
        "Khudai Khidmatgar",
        "Hindustan Republican Army",
        "Lal Sena"
      ],
      "answer": 0,
      "explanation": "The Indian National Army was popularly called the Azad Hind Fauj, meaning the Free India Army."
    },
    {
      "id": "indian-national-army-q02",
      "difficulty": "easy",
      "q": "Which leader revitalized and led the Indian National Army in 1943?",
      "options": [
        "Jawaharlal Nehru",
        "Mahatma Gandhi",
        "Subhas Chandra Bose",
        "Bhagat Singh"
      ],
      "answer": 2,
      "explanation": "Subhas Chandra Bose took over and reorganized the Indian National Army in 1943."
    },
    {
      "id": "indian-national-army-q03",
      "difficulty": "easy",
      "q": "In which broad region was the Indian National Army organized?",
      "options": [
        "North America",
        "Southeast Asia",
        "Western Europe",
        "East Africa"
      ],
      "answer": 1,
      "explanation": "The INA was organized among Indians in Southeast Asia to fight for India's independence."
    },
    {
      "id": "indian-national-army-q04",
      "difficulty": "easy",
      "q": "What was the primary aim of the Indian National Army?",
      "options": [
        "To defend British India from invasion",
        "To promote trade with Japan",
        "To establish a monarchy in India",
        "To fight for India's independence from British rule"
      ],
      "answer": 3,
      "explanation": "The INA was formed to fight for the liberation of India from British colonial rule."
    },
    {
      "id": "indian-national-army-q05",
      "difficulty": "easy",
      "q": "The title 'Netaji' is most closely associated with which INA leader?",
      "options": [
        "Mohan Singh",
        "Rash Behari Bose",
        "Subhas Chandra Bose",
        "Lakshmi Sahgal"
      ],
      "answer": 2,
      "explanation": "Subhas Chandra Bose, who led the INA, was popularly addressed as 'Netaji,' meaning respected leader."
    },
    {
      "id": "indian-national-army-q06",
      "difficulty": "easy",
      "q": "Which famous slogan is attributed to Subhas Chandra Bose and the INA?",
      "options": [
        "Give me blood, and I shall give you freedom",
        "Do or Die",
        "Simon Go Back",
        "Quit India"
      ],
      "answer": 0,
      "explanation": "Bose gave the call 'Give me blood, and I shall give you freedom' to inspire INA soldiers."
    },
    {
      "id": "indian-national-army-q07",
      "difficulty": "easy",
      "q": "The soldiers who first formed the INA were largely drawn from which group?",
      "options": [
        "British army officers",
        "Civilian shopkeepers",
        "Japanese marines",
        "Indian prisoners of war captured from the British army"
      ],
      "answer": 3,
      "explanation": "The INA was largely formed from Indian soldiers of the British Indian Army taken prisoner by Japan."
    },
    {
      "id": "indian-national-army-q08",
      "difficulty": "easy",
      "q": "During which global conflict did the Indian National Army carry out its main campaigns?",
      "options": [
        "The First World War",
        "The Second World War",
        "The Crimean War",
        "The Boer War"
      ],
      "answer": 1,
      "explanation": "The INA fought during the Second World War, alongside Japan against the British in the 1940s."
    },
    {
      "id": "indian-national-army-q09",
      "difficulty": "easy",
      "q": "The struggle of the Indian National Army had what notable effect within India?",
      "options": [
        "It ended the Congress party",
        "It inspired strong nationalist sentiment at home",
        "It restored Mughal rule",
        "It had no impact in India"
      ],
      "answer": 1,
      "explanation": "News of the INA's struggle stirred powerful nationalist feeling across India."
    },
    {
      "id": "indian-national-army-q10",
      "difficulty": "easy",
      "q": "The greeting 'Jai Hind' is popularly linked with which movement or force?",
      "options": [
        "The Royal Indian Navy",
        "The British Indian Police",
        "The Servants of India Society",
        "The Indian National Army"
      ],
      "answer": 3,
      "explanation": "'Jai Hind' was popularized as a salutation by the Indian National Army under Bose."
    },
    {
      "id": "indian-national-army-q11",
      "difficulty": "medium",
      "q": "Who is credited with first organizing the Indian National Army in 1942, before Bose took charge?",
      "options": [
        "Captain Mohan Singh",
        "General Cariappa",
        "Rash Behari Bose alone",
        "Lakshmi Sahgal"
      ],
      "answer": 0,
      "explanation": "Captain Mohan Singh formed the first INA in 1942 from Indian POWs, before it was reorganized under Bose."
    },
    {
      "id": "indian-national-army-q12",
      "difficulty": "medium",
      "q": "Which veteran revolutionary, long resident in Japan, helped lay the groundwork for the INA before handing leadership to Bose?",
      "options": [
        "M. N. Roy",
        "Lala Hardayal",
        "Rash Behari Bose",
        "Virendranath Chattopadhyaya"
      ],
      "answer": 2,
      "explanation": "Rash Behari Bose helped establish the Indian Independence League and INA, later passing leadership to Subhas Chandra Bose."
    },
    {
      "id": "indian-national-army-q13",
      "difficulty": "medium",
      "q": "The provisional government associated with the INA, proclaimed in 1943, was called what?",
      "options": [
        "The Indian Republic",
        "The Free Hindustan Council",
        "The Bengal Provisional State",
        "Azad Hind (Provisional Government of Free India)"
      ],
      "answer": 3,
      "explanation": "Bose proclaimed the Arzi Hukumat-e-Azad Hind, the Provisional Government of Free India, in October 1943."
    },
    {
      "id": "indian-national-army-q14",
      "difficulty": "medium",
      "q": "In which city did Subhas Chandra Bose proclaim the Provisional Government of Free India in October 1943?",
      "options": [
        "Tokyo",
        "Singapore",
        "Rangoon",
        "Bangkok"
      ],
      "answer": 1,
      "explanation": "Bose announced the Provisional Government of Free India in Singapore on 21 October 1943."
    },
    {
      "id": "indian-national-army-q15",
      "difficulty": "medium",
      "q": "Which foreign power allied with the INA during its campaigns in Southeast Asia?",
      "options": [
        "Germany",
        "Italy",
        "Japan",
        "The Soviet Union"
      ],
      "answer": 2,
      "explanation": "The INA fought alongside Imperial Japan against the British during the Second World War."
    },
    {
      "id": "indian-national-army-q16",
      "difficulty": "medium",
      "q": "The INA, alongside Japanese forces, took part in a major 1944 campaign aimed at entering India through which region?",
      "options": [
        "Imphal and Kohima in the northeast",
        "The Punjab in the northwest",
        "Bengal via the sea",
        "The Deccan plateau"
      ],
      "answer": 0,
      "explanation": "In 1944 the INA joined the Japanese offensive toward Imphal and Kohima on India's northeastern frontier."
    },
    {
      "id": "indian-national-army-q17",
      "difficulty": "medium",
      "q": "Which island territory did the Provisional Government of Free India claim authority over after Japan transferred it in 1943?",
      "options": [
        "Sri Lanka",
        "The Maldives",
        "The Andaman and Nicobar Islands",
        "The Lakshadweep Islands"
      ],
      "answer": 2,
      "explanation": "Japan handed nominal control of the Andaman and Nicobar Islands to the Azad Hind government in 1943."
    },
    {
      "id": "indian-national-army-q18",
      "difficulty": "medium",
      "q": "The INA's regiments were named after major national figures. Which of the following was an INA brigade or regiment name?",
      "options": [
        "The Gandhi Brigade",
        "The Curzon Brigade",
        "The Victoria Regiment",
        "The Clive Brigade"
      ],
      "answer": 0,
      "explanation": "INA units bore nationalist names such as the Gandhi Brigade, Azad Brigade and Nehru Brigade."
    },
    {
      "id": "indian-national-army-q19",
      "difficulty": "medium",
      "q": "What was the salutation popularized by the INA that later became a common patriotic greeting in India?",
      "options": [
        "Vande Mataram",
        "Inquilab Zindabad",
        "Bharat Mata ki Jai",
        "Jai Hind"
      ],
      "answer": 3,
      "explanation": "The INA popularized 'Jai Hind' (Victory to India), which endured as a patriotic greeting after independence."
    },
    {
      "id": "indian-national-army-q20",
      "difficulty": "medium",
      "q": "After Japan's surrender in 1945, what happened to the Indian National Army as a fighting force?",
      "options": [
        "It marched victoriously into Delhi",
        "It collapsed and many soldiers were taken prisoner",
        "It merged with the British Indian Army",
        "It relocated to Europe"
      ],
      "answer": 1,
      "explanation": "With Japan's defeat in 1945 the INA disintegrated, and many of its soldiers were captured by the British."
    },
    {
      "id": "indian-national-army-q21",
      "difficulty": "medium",
      "q": "Before leading the INA in Asia, Subhas Chandra Bose had organized an Indian unit in Europe alongside which power?",
      "options": [
        "Nazi Germany (the Indian Legion)",
        "Fascist Italy",
        "Vichy France",
        "Francoist Spain"
      ],
      "answer": 0,
      "explanation": "Bose first raised the Indian Legion in Germany before travelling to Southeast Asia to lead the INA."
    },
    {
      "id": "indian-national-army-q22",
      "difficulty": "medium",
      "q": "By what dramatic means did Subhas Chandra Bose travel from Germany to Southeast Asia in 1943?",
      "options": [
        "By commercial airliner",
        "By an overland caravan",
        "By a Japanese battleship",
        "By submarine"
      ],
      "answer": 3,
      "explanation": "Bose made the journey from Germany to Asia in 1943 by submarine, transferring between German and Japanese vessels."
    },
    {
      "id": "indian-national-army-q23",
      "difficulty": "hard",
      "q": "What was the name of the broader civilian organization in Southeast Asia from which the INA drew much of its support?",
      "options": [
        "The Servants of India Society",
        "The Indian Independence League",
        "The Forward Bloc",
        "The Anushilan Samiti"
      ],
      "answer": 1,
      "explanation": "The Indian Independence League mobilized the Indian diaspora in Southeast Asia in support of the INA."
    },
    {
      "id": "indian-national-army-q24",
      "difficulty": "hard",
      "q": "The first INA under Mohan Singh was dissolved in late 1942 chiefly because of what?",
      "options": [
        "A shortage of recruits",
        "A British counterattack",
        "Disputes over Japanese control and treatment of the army",
        "Mohan Singh's death"
      ],
      "answer": 2,
      "explanation": "The first INA was disbanded in December 1942 amid friction with the Japanese over the army's autonomy and role."
    },
    {
      "id": "indian-national-army-q25",
      "difficulty": "hard",
      "q": "On Indian soil during the 1944 advance, the INA is recorded as raising the national flag at which border location?",
      "options": [
        "Cox's Bazar",
        "Kohima town centre",
        "Dimapur",
        "Moirang in Manipur"
      ],
      "answer": 3,
      "explanation": "The INA hoisted the tricolour at Moirang in Manipur in April 1944, one of the few spots of Indian soil it reached."
    },
    {
      "id": "indian-national-army-q26",
      "difficulty": "hard",
      "q": "The INA's offensive toward Imphal in 1944 ultimately failed largely due to which factors?",
      "options": [
        "A mutiny by all its officers",
        "Monsoon conditions, supply shortages and a British counteroffensive",
        "Lack of any Japanese support",
        "An outbreak of plague in Singapore"
      ],
      "answer": 1,
      "explanation": "The Imphal-Kohima campaign collapsed amid the monsoon, severe supply problems, and a successful British counteroffensive."
    },
    {
      "id": "indian-national-army-q27",
      "difficulty": "hard",
      "q": "What anthem did the Provisional Government of Free India and the INA adopt?",
      "options": [
        "A version of 'Subh Sukh Chain' based on Tagore's song",
        "God Save the King",
        "Sare Jahan se Accha only",
        "The Internationale"
      ],
      "answer": 0,
      "explanation": "The INA adopted 'Subh Sukh Chain,' an adaptation of Rabindranath Tagore's song, as its anthem."
    },
    {
      "id": "indian-national-army-q28",
      "difficulty": "hard",
      "q": "The widely reported death of Subhas Chandra Bose in 1945 is associated with what event?",
      "options": [
        "A naval battle off Singapore",
        "An assassination in Rangoon",
        "A plane crash in Taiwan (then Formosa)",
        "A submarine accident"
      ],
      "answer": 2,
      "explanation": "Bose is widely reported to have died in a plane crash at Taihoku (Taipei) in August 1945, though some dispute the account."
    },
    {
      "id": "indian-national-army-q29",
      "difficulty": "hard",
      "q": "Several countries' Indian communities funded the INA. Bose's call for funds and recruits was especially strong among Indians in which countries?",
      "options": [
        "Canada and the United States",
        "Malaya and Burma",
        "South Africa and Kenya",
        "Fiji and Trinidad"
      ],
      "answer": 1,
      "explanation": "The Indian communities of Malaya and Burma provided crucial money and recruits for Bose's INA."
    },
    {
      "id": "indian-national-army-q30",
      "difficulty": "hard",
      "q": "The captured INA officers were later put on trial by the British at which historic location in 1945-46?",
      "options": [
        "The Cellular Jail in the Andamans",
        "Fort William in Calcutta",
        "The Lahore Fort",
        "The Red Fort in Delhi"
      ],
      "answer": 3,
      "explanation": "Captured INA officers were court-martialled at the Red Fort in Delhi in the celebrated INA trials of 1945-46."
    }
  ]
}