{
  "cardId": "mount-kailash",
  "questions": [
    {
      "id": "mount-kailash-q01",
      "difficulty": "easy",
      "q": "In the Puranas, Mount Kailash is revered as the eternal dwelling of which great deity?",
      "options": [
        "Vishnu",
        "Brahma",
        "Indra",
        "Shiva"
      ],
      "answer": 3,
      "explanation": "Mount Kailash is celebrated across the Puranas as the eternal abode of Shiva."
    },
    {
      "id": "mount-kailash-q02",
      "difficulty": "easy",
      "q": "In which mountain range is the sacred Mount Kailash traditionally located?",
      "options": [
        "The Himalayas",
        "The Vindhyas",
        "The Western Ghats",
        "The Aravallis"
      ],
      "answer": 0,
      "explanation": "Mount Kailash stands in the Himalayas, the great northern range of mountains."
    },
    {
      "id": "mount-kailash-q03",
      "difficulty": "easy",
      "q": "Which goddess is said to dwell alongside Shiva upon Mount Kailash as his consort?",
      "options": [
        "Lakshmi",
        "Parvati",
        "Saraswati",
        "Ganga"
      ],
      "answer": 1,
      "explanation": "Parvati, daughter of the mountain king Himavat, dwells with Shiva upon Mount Kailash as his consort."
    },
    {
      "id": "mount-kailash-q04",
      "difficulty": "easy",
      "q": "Which holy lake is most closely associated with Mount Kailash in Hindu tradition?",
      "options": [
        "Lake Pushkar",
        "Lake Pampa",
        "Lake Manasarovar",
        "Lake Bindusara"
      ],
      "answer": 2,
      "explanation": "Lake Manasarovar lies near Mount Kailash and is revered alongside it as a sacred site of pilgrimage."
    },
    {
      "id": "mount-kailash-q05",
      "difficulty": "easy",
      "q": "Mount Kailash is most famously honoured as the abode of Shiva in which of his aspects?",
      "options": [
        "A merchant of the marketplace",
        "A warrior charioteer",
        "A wandering minstrel",
        "The supreme ascetic in meditation"
      ],
      "answer": 3,
      "explanation": "Mount Kailash is described as the place where Shiva, the supreme ascetic, sits in deep meditation amid snow and ash."
    },
    {
      "id": "mount-kailash-q06",
      "difficulty": "easy",
      "q": "Besides Hindus, which of these traditions also holds Mount Kailash to be sacred?",
      "options": [
        "Jainism",
        "Shinto",
        "Zoroastrianism",
        "Confucianism"
      ],
      "answer": 0,
      "explanation": "Mount Kailash is held sacred by Jains, Buddhists, and Bon practitioners in addition to Hindus."
    },
    {
      "id": "mount-kailash-q07",
      "difficulty": "easy",
      "q": "Which sons of Shiva and Parvati are traditionally associated with the family that dwells on Mount Kailash?",
      "options": [
        "Rama and Lakshmana",
        "Ganesha and Kartikeya",
        "Nakula and Sahadeva",
        "Luv and Kush"
      ],
      "answer": 1,
      "explanation": "Ganesha and Kartikeya are the sons of Shiva and Parvati, the divine family associated with Mount Kailash."
    },
    {
      "id": "mount-kailash-q08",
      "difficulty": "easy",
      "q": "Which bull, the vahana of Shiva, is associated with the lord of Mount Kailash?",
      "options": [
        "Kamadhenu",
        "Garuda",
        "Nandi",
        "Airavata"
      ],
      "answer": 2,
      "explanation": "Nandi the bull is the faithful vahana and gatekeeper of Shiva, the lord of Mount Kailash."
    },
    {
      "id": "mount-kailash-q09",
      "difficulty": "easy",
      "q": "In Hindu tradition, what is the primary spiritual purpose for which devotees journey toward Mount Kailash?",
      "options": [
        "Trade and commerce",
        "Military conquest",
        "Royal coronation",
        "Pilgrimage and worship"
      ],
      "answer": 3,
      "explanation": "Mount Kailash and Lake Manasarovar are revered as a great destination of pilgrimage and worship."
    },
    {
      "id": "mount-kailash-q10",
      "difficulty": "easy",
      "q": "In the lore of the Puranas, Mount Kailash is often described as the still centre, or axis, of what?",
      "options": [
        "The cosmos",
        "The ocean",
        "A single kingdom",
        "A forest"
      ],
      "answer": 0,
      "explanation": "Mount Kailash is revered as the still axis of the cosmos where the great ascetic abides."
    },
    {
      "id": "mount-kailash-q11",
      "difficulty": "medium",
      "q": "Which rakshasa king is said in the Ramayana to have attempted to lift and carry away Mount Kailash?",
      "options": [
        "Kumbhakarna",
        "Ravana",
        "Vibhishana",
        "Indrajit"
      ],
      "answer": 1,
      "explanation": "In the Ramayana, the demon king Ravana attempted to uproot Mount Kailash, the abode of Shiva."
    },
    {
      "id": "mount-kailash-q12",
      "difficulty": "medium",
      "q": "When Ravana tried to lift Mount Kailash, how did Shiva subdue him according to the tradition?",
      "options": [
        "By hurling his trident",
        "By summoning a flood",
        "By pressing the mountain down with his toe",
        "By turning him to stone"
      ],
      "answer": 2,
      "explanation": "Shiva pressed Mount Kailash down with his toe, trapping Ravana beneath until the demon sang his praises."
    },
    {
      "id": "mount-kailash-q13",
      "difficulty": "medium",
      "q": "The hymn that Ravana is said to have composed in praise of Shiva while pinned beneath Mount Kailash is traditionally known as which work?",
      "options": [
        "The Vishnu Sahasranama",
        "The Hanuman Chalisa",
        "The Gayatri Mantra",
        "The Shiva Tandava Stotra"
      ],
      "answer": 3,
      "explanation": "Tradition holds that Ravana composed the Shiva Tandava Stotra in praise of Shiva while trapped beneath Mount Kailash."
    },
    {
      "id": "mount-kailash-q14",
      "difficulty": "medium",
      "q": "Parvati, who dwells on Mount Kailash with Shiva, is the daughter of which mountain king?",
      "options": [
        "Himavat",
        "Janaka",
        "Jambavan",
        "Bali"
      ],
      "answer": 0,
      "explanation": "Parvati is the daughter of Himavat, the personified king of the Himalaya mountains."
    },
    {
      "id": "mount-kailash-q15",
      "difficulty": "medium",
      "q": "Which guardian of wealth, lord of the yakshas, is described in the Puranas as having his city Alaka near Mount Kailash?",
      "options": [
        "Varuna",
        "Kubera",
        "Yama",
        "Agni"
      ],
      "answer": 1,
      "explanation": "Kubera, lord of wealth and the yakshas, is said to rule his city Alaka in the region of Mount Kailash."
    },
    {
      "id": "mount-kailash-q16",
      "difficulty": "medium",
      "q": "The sacred river Ganga is connected to Shiva of Mount Kailash through which well-known account?",
      "options": [
        "She was churned from the ocean",
        "She was born from Brahma's tears",
        "She descended from heaven into Shiva's matted locks",
        "She emerged from a lotus"
      ],
      "answer": 2,
      "explanation": "In the Puranas, Ganga descended from heaven and was received in Shiva's matted locks to break her fall to earth."
    },
    {
      "id": "mount-kailash-q17",
      "difficulty": "medium",
      "q": "Lake Manasarovar, near Mount Kailash, is traditionally said in the Puranas to have first been formed in the mind of which deity?",
      "options": [
        "Yama",
        "Surya",
        "Vayu",
        "Brahma"
      ],
      "answer": 3,
      "explanation": "The Puranas relate that Lake Manasarovar was first conceived in the mind of Brahma, giving it its name from 'manas', the mind."
    },
    {
      "id": "mount-kailash-q18",
      "difficulty": "medium",
      "q": "Which weapon is most characteristically held by Shiva, the lord enthroned upon Mount Kailash?",
      "options": [
        "The trident (trishula)",
        "The Sudarshana Chakra",
        "The Vajra",
        "The Sharanga bow"
      ],
      "answer": 0,
      "explanation": "The trident, or trishula, is the characteristic weapon of Shiva, the lord of Mount Kailash."
    },
    {
      "id": "mount-kailash-q19",
      "difficulty": "medium",
      "q": "The cosmic golden mountain Mount Meru, sometimes likened to or associated with Kailash, is described in the Puranas as standing at the centre of what?",
      "options": [
        "The underworld",
        "The world or universe",
        "A single ocean",
        "The city of Lanka"
      ],
      "answer": 1,
      "explanation": "Mount Meru is described in the Puranas as the golden axis standing at the centre of the world and universe."
    },
    {
      "id": "mount-kailash-q20",
      "difficulty": "medium",
      "q": "In Hindu cosmology, Mount Kailash as the seat of Shiva is regarded primarily as a place of which quality?",
      "options": [
        "Worldly indulgence",
        "Constant warfare",
        "Supreme sanctity and meditation",
        "Mercantile bustle"
      ],
      "answer": 2,
      "explanation": "Mount Kailash is regarded as a place of supreme sanctity where Shiva abides in meditation."
    },
    {
      "id": "mount-kailash-q21",
      "difficulty": "medium",
      "q": "Which serpent does Shiva, the lord of Mount Kailash, traditionally wear coiled about his neck?",
      "options": [
        "Kaliya",
        "Takshaka",
        "Karkotaka",
        "Vasuki"
      ],
      "answer": 3,
      "explanation": "Shiva is depicted wearing the serpent Vasuki coiled about his neck as an ornament."
    },
    {
      "id": "mount-kailash-q22",
      "difficulty": "medium",
      "q": "The crescent moon worn by Shiva upon Mount Kailash gives him which well-known epithet?",
      "options": [
        "Chandrashekhara",
        "Gajanana",
        "Madhusudana",
        "Padmanabha"
      ],
      "answer": 0,
      "explanation": "Bearing the crescent moon in his hair, Shiva is called Chandrashekhara, 'the one crowned with the moon'."
    },
    {
      "id": "mount-kailash-q23",
      "difficulty": "hard",
      "q": "After Ravana was pinned beneath Mount Kailash and won Shiva's favour through his hymn, which mighty sword is he traditionally said to have received?",
      "options": [
        "Nandaka",
        "Chandrahasa",
        "Gandiva",
        "Vijaya"
      ],
      "answer": 1,
      "explanation": "Tradition holds that a pleased Shiva granted Ravana the celebrated sword Chandrahasa after his hymn from beneath Mount Kailash."
    },
    {
      "id": "mount-kailash-q24",
      "difficulty": "hard",
      "q": "Among the four great rivers said in the Puranas to arise in the region of Mount Kailash and Manasarovar, which is named here?",
      "options": [
        "Yamuna",
        "Godavari",
        "Brahmaputra",
        "Kaveri"
      ],
      "answer": 2,
      "explanation": "The Brahmaputra is counted among the great rivers traditionally said to originate in the sacred region around Mount Kailash."
    },
    {
      "id": "mount-kailash-q25",
      "difficulty": "hard",
      "q": "In the Puranas, Mount Kailash is sometimes likened to a great linga or to which sacred symbol of Shiva's presence?",
      "options": [
        "A golden chariot",
        "A jewelled crown",
        "A silver bow",
        "A flaming pillar of light"
      ],
      "answer": 3,
      "explanation": "Shiva is described in the Puranas as a boundless pillar of light, an image echoed in the reverence for Mount Kailash as his seat."
    },
    {
      "id": "mount-kailash-q26",
      "difficulty": "hard",
      "q": "Which sage, often depicted in the celestial court near Shiva's abode, is renowned in the Puranas for wandering the worlds chanting the name of Narayana?",
      "options": [
        "Narada",
        "Vishvamitra",
        "Durvasa",
        "Bhrigu"
      ],
      "answer": 0,
      "explanation": "The sage Narada is famed in the Puranas for travelling the worlds, including Shiva's realm, chanting the name of Narayana."
    },
    {
      "id": "mount-kailash-q27",
      "difficulty": "hard",
      "q": "In Buddhist tradition, the sacred peak identified with Mount Kailash is especially associated with which figure?",
      "options": [
        "Confucius",
        "Chakrasamvara",
        "Mahavira",
        "Zoroaster"
      ],
      "answer": 1,
      "explanation": "In Buddhist tradition the peak of Kailash is associated with the deity Chakrasamvara, reflecting the mountain's shared sanctity."
    },
    {
      "id": "mount-kailash-q28",
      "difficulty": "hard",
      "q": "In Jain tradition, Mount Kailash, known to them as Ashtapada, is revered as the place where which Tirthankara attained liberation?",
      "options": [
        "Mahavira",
        "Parshvanatha",
        "Rishabhanatha",
        "Neminatha"
      ],
      "answer": 2,
      "explanation": "In Jain tradition, Mount Kailash, called Ashtapada, is revered as the site where the first Tirthankara Rishabhanatha attained liberation."
    },
    {
      "id": "mount-kailash-q29",
      "difficulty": "hard",
      "q": "The pre-Buddhist tradition of Tibet that also venerates Mount Kailash as a sacred centre is known by which name?",
      "options": [
        "Jain",
        "Sikh",
        "Vaishnava",
        "Bon"
      ],
      "answer": 3,
      "explanation": "The Bon tradition, native to Tibet, venerates Mount Kailash as a sacred spiritual centre."
    },
    {
      "id": "mount-kailash-q30",
      "difficulty": "hard",
      "q": "In the Puranas, the radiant city of the gods set upon the golden cosmic mountain near these heights, where Indra and the devas dwell, is named what?",
      "options": [
        "Amaravati",
        "Dwaraka",
        "Indraprastha",
        "Hastinapura"
      ],
      "answer": 0,
      "explanation": "Amaravati is described in the Puranas as the celestial city of Indra and the devas amid the cosmic heights."
    }
  ]
}
